Auto_Sphinx/__init__.py
Auto_Sphinx/tasks.py
Auto_Sphinx_willyt123-0.0.1.dist-info/LICENSE
Auto_Sphinx_willyt123-0.0.1.dist-info/METADATA
Auto_Sphinx_willyt123-0.0.1.dist-info/WHEEL
Auto_Sphinx_willyt123-0.0.1.dist-info/top_level.txt
Auto_Sphinx_willyt123-0.0.1.dist-info/RECORD
